MANIFEST.in
README.md
requirements_cli.txt
setup.py
client/__init__.py
client/__main__.py
client/abstractions.py
client/cli_utils.py
client/command_handler.py
client/forkie.py
forkieCLI.egg-info/PKG-INFO
forkieCLI.egg-info/SOURCES.txt
forkieCLI.egg-info/dependency_links.txt
forkieCLI.egg-info/entry_points.txt
forkieCLI.egg-info/requires.txt
forkieCLI.egg-info/top_level.txt
src/__init__.py
src/api/__init__.py
src/api/files/__init__.py
src/api/files/archiveCron.py
src/api/files/backblaze.py
src/api/files/file_archive.py
src/api/files/file_compare.py
src/api/files/file_create.py
src/api/files/file_delete.py
src/api/files/file_query.py
src/api/files/utils.py