Metadata-Version: 2.1
Name: forkieCLI
Version: 0.0.2
Summary: The CLI tool for the forkie file versioning system
Home-page: https://github.com/RHUL-CS-Projects/CS1813_2020_09
Author: Jakab Zeller
Author-email: jakabzeller0@gmail.com
License: UNKNOWN
Platform: UNKNOWN
Classifier: Programming Language :: Python :: 3
Classifier: Operating System :: OS Independent
Requires-Python: >=3
